setpy.py
setpy-0.0.3.dist-info/LICENSE.txt
setpy-0.0.3.dist-info/METADATA
setpy-0.0.3.dist-info/WHEEL
setpy-0.0.3.dist-info/top_level.txt
setpy-0.0.3.dist-info/RECORD
