Metadata-Version: 2.1
Name: setpy
Version: 0.0.3
Summary: A small example package
Home-page: https://github.com/makertech81/setpy
Author: TJ Ledwith
Author-email: tjledwith1@gmail.com
License: UNKNOWN
Platform: UNKNOWN
Classifier: Programming Language :: Python :: 3
Classifier: License :: OSI Approved :: MIT License
Classifier: Operating System :: OS Independent
Requires-Python: >=3.6
Requires-Dist: numpy (~=1.15)
Requires-Dist: matplotlib (~=3.3.0)
